catalyst/__init__.py
catalyst/__version__.py
catalyst/registry.py
catalyst/settings.py
catalyst/typing.py
catalyst/callbacks/__init__.py
catalyst/callbacks/backward.py
catalyst/callbacks/batch_overfit.py
catalyst/callbacks/batch_transform.py
catalyst/callbacks/checkpoint.py
catalyst/callbacks/control_flow.py
catalyst/callbacks/criterion.py
catalyst/callbacks/metric.py
catalyst/callbacks/metric_aggregation.py
catalyst/callbacks/misc.py
catalyst/callbacks/mixup.py
catalyst/callbacks/onnx.py
catalyst/callbacks/optimizer.py
catalyst/callbacks/optuna.py
catalyst/callbacks/periodic_loader.py
catalyst/callbacks/profiler.py
catalyst/callbacks/pruning.py
catalyst/callbacks/quantization.py
catalyst/callbacks/scheduler.py
catalyst/callbacks/sklearn_model.py
catalyst/callbacks/soft_update.py
catalyst/callbacks/tracing.py
catalyst/callbacks/metrics/__init__.py
catalyst/callbacks/metrics/accuracy.py
catalyst/callbacks/metrics/auc.py
catalyst/callbacks/metrics/classification.py
catalyst/callbacks/metrics/cmc_score.py
catalyst/callbacks/metrics/confusion_matrix.py
catalyst/callbacks/metrics/functional_metric.py
catalyst/callbacks/metrics/r2_squared.py
catalyst/callbacks/metrics/recsys.py
catalyst/callbacks/metrics/scikit_learn.py
catalyst/callbacks/metrics/segmentation.py
catalyst/contrib/__init__.py
catalyst/contrib/__main__.py
catalyst/contrib/data/__init__.py
catalyst/contrib/data/_misc.py
catalyst/contrib/data/collate_fn.py
catalyst/contrib/data/dataset.py
catalyst/contrib/data/dataset_cv.py
catalyst/contrib/data/dataset_ml.py
catalyst/contrib/data/reader.py
catalyst/contrib/data/reader_cv.py
catalyst/contrib/data/sampler.py
catalyst/contrib/data/sampler_inbatch.py
catalyst/contrib/data/transforms.py
catalyst/contrib/datasets/__init__.py
catalyst/contrib/datasets/cifar.py
catalyst/contrib/datasets/imagecar.py
catalyst/contrib/datasets/imagenette.py
catalyst/contrib/datasets/imagewang.py
catalyst/contrib/datasets/imagewoof.py
catalyst/contrib/datasets/market1501.py
catalyst-22.4.dist-info/LICENSE
catalyst-22.4.dist-info/METADATA
catalyst-22.4.dist-info/WHEEL
catalyst-22.4.dist-info/entry_points.txt
catalyst-22.4.dist-info/top_level.txt
catalyst-22.4.dist-info/RECORD
