Metadata-Version: 2.1
Name: catalyst
Version: 22.4
Summary: Catalyst. Accelerated deep learning R&D with PyTorch.
Home-page: https://github.com/catalyst-team/catalyst
Download-URL: https://github.com/catalyst-team/catalyst
Author: Sergey Kolesnikov
Author-email: scitator@gmail.com
License: Apache License 2.0
Project-URL: Bug Tracker, https://github.com/catalyst-team/catalyst/issues
Project-URL: Documentation, https://catalyst-team.github.io/catalyst
Project-URL: Source Code, https://github.com/catalyst-team/catalyst
Keywords: Machine Learning,Distributed Computing,Deep Learning,Reinforcement Learning,Computer Vision,Natural Language Processing,Recommendation Systems,Information Retrieval,PyTorch
Platform: UNKNOWN
Classifier: Environment :: Console
Classifier: Natural Language :: English
Classifier: Development Status :: 4 - Beta
Classifier: Operating System :: OS Independent
Classifier: License :: OSI Approved :: Apache Software License
Classifier: Intended Audience :: Developers
Classifier: Intended Audience :: Science/Research
Classifier: Topic :: Scientific/Engineering :: Artificial Intelligence
Classifier: Topic :: Scientific/Engineering :: Image Recognition
Classifier: Topic :: Scientific/Engineering :: Information Analysis
Classifier: Programming Language :: Python
Classifier: Programming Language :: Python :: 3.7
Classifier: Programming Language :: Python :: 3.8
Classifier: Programming Language :: Python :: 3.9
Classifier: Programming Language :: Python :: 3.10
Classifier: Programming Language :: Python :: Implementation :: CPython
Requires-Python: >=3.7.0
License-File: LICENSE
Requires-Dist: numpy (>=1.18)
Requires-Dist: torch (>=1.4.0)
Requires-Dist: accelerate (>=0.5.1)
Requires-Dist: hydra-slayer (>=0.4.0)
Requires-Dist: tqdm (>=4.33.0)
Requires-Dist: tensorboardX (>=2.1.0)
Provides-Extra: all
Requires-Dist: imageio (>=2.5.0) ; extra == 'all'
Requires-Dist: opencv-python-headless (>=4.2.0.32) ; extra == 'all'
Requires-Dist: scikit-image (<0.19.0>=0.16.1) ; extra == 'all'
Requires-Dist: torchvision (>=0.5.0) ; extra == 'all'
Requires-Dist: Pillow (>=6.1) ; extra == 'all'
Requires-Dist: requests ; extra == 'all'
Requires-Dist: scipy (>=1.4.1) ; extra == 'all'
Requires-Dist: matplotlib (>=3.1.0) ; extra == 'all'
Requires-Dist: pandas (>=1.0.0) ; extra == 'all'
Requires-Dist: scikit-learn (>=1.0) ; extra == 'all'
Requires-Dist: optuna (>=2.0.0) ; extra == 'all'
Provides-Extra: comet
Requires-Dist: comet-ml ; extra == 'comet'
Provides-Extra: cv
Requires-Dist: imageio (>=2.5.0) ; extra == 'cv'
Requires-Dist: opencv-python-headless (>=4.2.0.32) ; extra == 'cv'
Requires-Dist: scikit-image (<0.19.0>=0.16.1) ; extra == 'cv'
Requires-Dist: torchvision (>=0.5.0) ; extra == 'cv'
Requires-Dist: Pillow (>=6.1) ; extra == 'cv'
Requires-Dist: requests ; extra == 'cv'
Provides-Extra: deepspeed
Requires-Dist: deepspeed (>=0.4.0) ; extra == 'deepspeed'
Provides-Extra: dev
Requires-Dist: pytest ; extra == 'dev'
Requires-Dist: sphinx (==2.2.1) ; extra == 'dev'
Requires-Dist: Jinja2 (<=3.0.3) ; extra == 'dev'
Requires-Dist: docutils (==0.17.1) ; extra == 'dev'
Requires-Dist: mock (==3.0.5) ; extra == 'dev'
Requires-Dist: catalyst-codestyle (==21.09.2) ; extra == 'dev'
Requires-Dist: black (==21.8b0) ; extra == 'dev'
Requires-Dist: click (<=8.0.4) ; extra == 'dev'
Requires-Dist: catalyst-sphinx-theme (==1.2.0) ; extra == 'dev'
Requires-Dist: tomlkit (==0.7.2) ; extra == 'dev'
Requires-Dist: pre-commit (==2.13.0) ; extra == 'dev'
Requires-Dist: path ; extra == 'dev'
Provides-Extra: ml
Requires-Dist: scipy (>=1.4.1) ; extra == 'ml'
Requires-Dist: matplotlib (>=3.1.0) ; extra == 'ml'
Requires-Dist: pandas (>=1.0.0) ; extra == 'ml'
Requires-Dist: scikit-learn (>=1.0) ; extra == 'ml'
Provides-Extra: mlflow
Requires-Dist: mlflow ; extra == 'mlflow'
Provides-Extra: neptune
Requires-Dist: neptune-client (>=0.9.8) ; extra == 'neptune'
Provides-Extra: onnx
Requires-Dist: onnx ; extra == 'onnx'
Requires-Dist: onnxruntime ; extra == 'onnx'
Provides-Extra: onnx-gpu
Requires-Dist: onnx ; extra == 'onnx-gpu'
Requires-Dist: onnxruntime-gpu ; extra == 'onnx-gpu'
Provides-Extra: optuna
Requires-Dist: optuna (>=2.0.0) ; extra == 'optuna'
Provides-Extra: profiler
Requires-Dist: torch-tb-profiler ; extra == 'profiler'
Provides-Extra: wandb
Requires-Dist: wandb ; extra == 'wandb'
